jjc_backend/__init__.py
jjc_backend/foo.py
jjc_backend-0.0.1.dist-info/METADATA
jjc_backend-0.0.1.dist-info/WHEEL
jjc_backend-0.0.1.dist-info/licenses/LICENSE
jjc_backend-0.0.1.dist-info/RECORD
