Metadata-Version: 2.4
Name: jjc-backend
Version: 0.0.1
Summary: This is the django-backend of JourneyJinks Canvas.
Project-URL: Homepage, https://makanu.github.io/jjc-backend/
Project-URL: Repository, https://github.com/makanu/jjc-backend
Project-URL: Documentation, https://makanu.github.io/jjc-backend/
Author-email: MaKaNu <matti.kaupenjohann@fh-dortmund.de>
License-File: LICENSE
Keywords: python
Classifier: Intended Audience :: Developers
Classifier: Programming Language :: Python
Classifier: Programming Language :: Python :: 3
Classifier: Programming Language :: Python :: 3.9
Classifier: Programming Language :: Python :: 3.10
Classifier: Programming Language :: Python :: 3.11
Classifier: Programming Language :: Python :: 3.12
Classifier: Programming Language :: Python :: 3.13
Classifier: Topic :: Software Development :: Libraries :: Python Modules
Requires-Python: <4.0,>=3.9
